[
	{"agent":"香港评值国际有限公司","businessType":"评估机构","applicateTime":"2018.5.8"},
	{"agent":"新天域资本","businessType":"金融机构","applicateTime":"2018.5.8"},
	{"agent":"张德城(注册会计师)","businessType":"注册会计师","applicateTime":"2018.5.8"},
	{"agent":"张德城(律师)","businessType":"律师","applicateTime":"2018.5.8"},
	{"agent":"天虹资本","businessType":"理财顾问","applicateTime":"2018.5.8"},
	{"agent":"香港投资顾问有限公司","businessType":"投资顾问","applicateTime":"2018.5.8"},
	{"agent":"香港评值国际有限公司","businessType":"分析师","applicateTime":"2018.5.8"},
	{"agent":"新天域资本","businessType":"证券理财师","applicateTime":"2018.5.8"},
	{"agent":"张德城(注册会计师)","businessType":"评估机构","applicateTime":"2018.5.8"},
	{"agent":"张德城(律师)","businessType":"律师","applicateTime":"2018.5.8"},
	{"agent":"新亚瑟投资公司","businessType":"注册会计师","applicateTime":"2018.5.8"},
	{"agent":"天盛资本","businessType":"投资顾问","applicateTime":"2018.5.8"}

]